server_data_server/__init__.py
server_data_server/__main__.py
server_data_server/template/app.py
server_data_server/template/config.json
server_data_server/template/requirements.txt
server_data_server-0.0.1.dist-info/METADATA
server_data_server-0.0.1.dist-info/WHEEL
server_data_server-0.0.1.dist-info/entry_points.txt
server_data_server-0.0.1.dist-info/top_level.txt
server_data_server-0.0.1.dist-info/RECORD
